stackedit/__init__.py
stackedit/admin.py
stackedit/api.py
stackedit/fields.py
stackedit/models.py
stackedit/settings.py
stackedit/urls.py
stackedit/utils.py
stackedit/views.py
stackedit/widgets.py
stackedit/extensions/__init__.py
stackedit/extensions/del_ins.py
stackedit/extensions/emoji.py
stackedit/extensions/mdx_video.py
stackedit/extensions/mention.py
stackedit/extensions/urlize.py
stackedit/templatetags/__init__.py
stackedit/templatetags/martortags.py
stackedit/tests/__init__.py
stackedit/tests/models.py
stackedit/tests/tests.py
stackedit/tests/urls.py
stackedit/tests/views.py
django_stackedit-0.0.1.dist-info/LICENSE
django_stackedit-0.0.1.dist-info/METADATA
django_stackedit-0.0.1.dist-info/WHEEL
django_stackedit-0.0.1.dist-info/top_level.txt
django_stackedit-0.0.1.dist-info/RECORD
