Metadata-Version: 2.1
Name: django-stackedit
Version: 0.0.1
Summary: Django Stackedit Markdown Editor
Home-page: https://gitee.com/qtch/django-stackedit
Author: Peter Han (Qitian)
Author-email: peter@qitian.biz
License: GNUGPL-v3
Keywords: stackedit,django markdown,django markdown editor
Platform: UNKNOWN
Classifier: Development Status :: 5 - Production/Stable
Classifier: Environment :: Web Environment
Classifier: Framework :: Django
Classifier: Framework :: Django :: 1.8
Classifier: Framework :: Django :: 1.9
Classifier: Framework :: Django :: 1.10
Classifier: Framework :: Django :: 1.11
Classifier: Framework :: Django :: 2.0
Classifier: Framework :: Django :: 2.1
Classifier: Intended Audience :: Developers
Classifier: Operating System :: OS Independent
Classifier: Programming Language :: JavaScript
Classifier: Programming Language :: Python
Classifier: Programming Language :: Python :: 2.7
Classifier: Programming Language :: Python :: 3.4
Classifier: Programming Language :: Python :: 3.5
Classifier: Programming Language :: Python :: 3.6
Classifier: Topic :: Software Development :: Libraries :: Python Modules
Classifier: License :: OSI Approved :: GNU General Public License v3 (GPLv3)
Requires-Dist: Django
Requires-Dist: Markdown
Requires-Dist: requests
Requires-Dist: wheel
Requires-Dist: twine
